tiniestsegmenter-0.3.0.dist-info/METADATA
tiniestsegmenter-0.3.0.dist-info/WHEEL
tiniestsegmenter-0.3.0.dist-info/licenses/LICENSE
tiniestsegmenter/__init__.py
tiniestsegmenter/py.typed
tiniestsegmenter/tiniestsegmenter.pyi
tiniestsegmenter/tiniestsegmenter.cpython-310-darwin.so
tiniestsegmenter-0.3.0.dist-info/RECORD
