Metadata-Version: 2.3
Name: tiniestsegmenter
Version: 0.3.0
Classifier: License :: OSI Approved :: MIT License
Classifier: Programming Language :: Rust
Classifier: Topic :: Text Editors :: Text Processing
License-File: LICENSE
Summary: Compact Japanese segmenter
Keywords: tokenizer,NLP,ngram,Japanese
Author: Teryn Jones
Requires-Python: >=3.8
Project-URL: Homepage, https://github.com/jwnz/tiniestsegmenter
Project-URL: Repository, https://github.com/jwnz/tiniestsegmenter
Project-URL: Issues, https://github.com/jwnz/tiniestsegmenter/issues
